davar/__init__.py
davar/__main__.py
davar/model.py
davar/parsing.py
davar/utils.py
LICENSE
davar-0.2.0.dist-info/LICENSE
davar-0.2.0.dist-info/WHEEL
davar-0.2.0.dist-info/METADATA
davar-0.2.0.dist-info/RECORD
