Metadata-Version: 2.1
Name: davar
Version: 0.2.0
Summary: An experimental interpreted international auxiliary language.
Home-page: https://github.com/impossiblynew/davar
License: MIT
Keywords: language,translation,WikiData
Author: Impossibly New
Author-email: newlyimpossible@gmail.com
Requires-Python: >=3.7,<4.0
Classifier: Development Status :: 2 - Pre-Alpha
Classifier: Environment :: Console
Classifier: License :: OSI Approved :: MIT License
Classifier: Operating System :: OS Independent
Classifier: Programming Language :: Python :: 3
Classifier: Programming Language :: Python :: 3.7
Classifier: Programming Language :: Python :: 3.8
Classifier: Topic :: Communications
Classifier: Topic :: Database
Classifier: Topic :: Internet :: WWW/HTTP :: Dynamic Content :: Wiki
Classifier: Topic :: Text Processing :: Linguistic
Requires-Dist: arpeggio (>=1.9.2,<2.0.0)
Requires-Dist: nltk (>=3.5,<4.0)
Requires-Dist: pycountry (>=19.8.18,<20.0.0)
Requires-Dist: wikidata (>=0.6.1,<0.7.0)
Project-URL: Repository, https://github.com/impossiblynew/davar
